rfxcom/__init__.py
rfxcom/exceptions.py
rfxcom/protocol/elec.py
rfxcom/protocol/status.py
rfxcom/protocol/lighting5.py
rfxcom/protocol/base.py
rfxcom/protocol/__init__.py
rfxcom/protocol/temphumidity.py
rfxcom/transport/base.py
rfxcom/transport/__init__.py
rfxcom/transport/asyncio.py
rfxcom-0.5.0.dist-info/DESCRIPTION.rst
rfxcom-0.5.0.dist-info/RECORD
rfxcom-0.5.0.dist-info/METADATA
rfxcom-0.5.0.dist-info/WHEEL
rfxcom-0.5.0.dist-info/top_level.txt
rfxcom-0.5.0.dist-info/metadata.json
